pyapiary/__init__.py
pyapiary/api_connectors/__init__.py
pyapiary/api_connectors/broker.py
pyapiary/api_connectors/flashpoint.py
pyapiary/api_connectors/generic.py
pyapiary/api_connectors/ipqs.py
pyapiary/api_connectors/spycloud.py
pyapiary/api_connectors/twilio.py
pyapiary/api_connectors/urlscan.py
pyapiary/dbms_connectors/__init__.py
pyapiary/dbms_connectors/elasticsearch.py
pyapiary/dbms_connectors/mongo.py
pyapiary/dbms_connectors/mongo_async.py
pyapiary/dbms_connectors/odbc.py
pyapiary/dbms_connectors/splunk.py
pyapiary/helpers.py
pyapiary/tests/__init__.py
pyapiary/tests/conftest.py
pyapiary/tests/test_broker/test_integration_broker.py
pyapiary/tests/test_broker/test_unit_asyncbroker.py
pyapiary/tests/test_broker/test_unit_broker.py
pyapiary/tests/test_elasticsearch/test_unit_elasticsearch.py
pyapiary/tests/test_flashpoint/cassettes/test_flashpoint_search_fraud_vcr.yaml
pyapiary/tests/test_flashpoint/test_integration_flashpoint.py
pyapiary/tests/test_flashpoint/test_unit_async_flashpoint.py
pyapiary/tests/test_flashpoint/test_unit_flashpoint.py
pyapiary/tests/test_generic/cassettes/test_generic_get_github_api.yaml
pyapiary/tests/test_generic/test_integration_generic_connector.py
pyapiary/tests/test_generic/test_unit_async_generic_connector.py
pyapiary/tests/test_generic/test_unit_generic_connector.py
pyapiary/tests/test_ipqs/__init__.py
pyapiary/tests/test_ipqs/cassettes/test_ipqs_malicious_url_vcr.yaml
pyapiary/tests/test_ipqs/test_integration_ipqs.py
pyapiary/tests/test_ipqs/test_unit_async_ipqs.py
pyapiary/tests/test_ipqs/test_unit_ipqs.py
pyapiary/tests/test_mongodb/test_unit_async_mongo.py
pyapiary/tests/test_mongodb/test_unit_mongo.py
pyapiary/tests/test_odbc/test_unit_odbc.py
pyapiary/tests/test_splunk/test_unit_splunk.py
pyapiary/tests/test_spycloud/cassettes/test_spycloud_ato_search_vcr.yaml
pyapiary/tests/test_spycloud/test_integration_spycloud.py
pyapiary/tests/test_spycloud/test_unit_async_spycloud.py
pyapiary-2.0.0.dist-info/METADATA
pyapiary-2.0.0.dist-info/WHEEL
pyapiary-2.0.0.dist-info/RECORD
