Metadata-Version: 2.4
Name: pyapiary
Version: 2.0.0
Summary: A simple, lightweight set of connectors and functions to various APIs and DBMSs, controlled by a central broker.
Author: Rob D'Aveta
Author-email: rob.daveta@gmail.com
Requires-Python: >=3.10,<4.0
Classifier: Programming Language :: Python :: 3
Classifier: Programming Language :: Python :: 3.10
Classifier: Programming Language :: Python :: 3.11
Classifier: Programming Language :: Python :: 3.12
Classifier: Programming Language :: Python :: 3.13
Classifier: Programming Language :: Python :: 3.14
Provides-Extra: odbc
Requires-Dist: elasticsearch (>=9.1.1,<10.0.0)
Requires-Dist: httpx (>=0.28.1,<0.29.0)
Requires-Dist: pymongo (>=4.15.0,<5.0.0)
Requires-Dist: pyodbc (>=5.3.0,<6.0.0) ; extra == "odbc"
Requires-Dist: python-dotenv (>=1.1.1,<2.0.0)
Requires-Dist: splunk-sdk (>=2.1.1,<3.0.0)
Requires-Dist: tenacity (>=9.1.2,<10.0.0)
Project-URL: Homepage, https://github.com/robd518/pyapiary
Project-URL: Repository, https://github.com/robd518/pyapiary
